{
  "timestamp": 1773291843091,
  "gitStatus": "M history/cross_instance_dialogue.json\n M history/session_1773286908254.json\n?? projects/CAMPO_KAINOS_VISUAL_1773291812.md",
  "codeMetrics": {
    "totalFiles": 187,
    "totalLines": 22541,
    "testFiles": 94,
    "implementationFiles": 93,
    "testCoverage": 101.0752688172043,
    "lastModified": "2026-03-04T21:07:13.336Z"
  },
  "memoryStatus": {
    "planExists": true,
    "lastSessionExists": true
  },
  "recommendations": [
    "Working directory has uncommitted changes"
  ]
}